package.json
nbdefense_jupyter/__init__.py
nbdefense_jupyter/_version.py
nbdefense_jupyter/handlers.py
nbdefense_jupyter/labextension/package.json
nbdefense_jupyter/labextension/schemas/nbdefense-jupyter/package.json.orig
nbdefense_jupyter/labextension/schemas/nbdefense-jupyter/plugin.json
nbdefense_jupyter/labextension/static/239.1c003b0dfd58bc7823a8.js
nbdefense_jupyter/labextension/static/355.e71f4acc9570680d68e9.js
nbdefense_jupyter/labextension/static/452.26450d70ddf6735bc3a7.js
nbdefense_jupyter/labextension/static/452.26450d70ddf6735bc3a7.js.LICENSE.txt
nbdefense_jupyter/labextension/static/500.97d1a5336e530d36f1c4.js
nbdefense_jupyter/labextension/static/502.ab49aeea7a0fb1ad88e8.js
nbdefense_jupyter/labextension/static/502.ab49aeea7a0fb1ad88e8.js.LICENSE.txt
nbdefense_jupyter/labextension/static/654.0b96d4d60115144c75b2.js
nbdefense_jupyter/labextension/static/661.42dcb7cf7c20838bfd42.js
nbdefense_jupyter/labextension/static/676.6137834929c84786225d.js
nbdefense_jupyter/labextension/static/747.5ffca1b512bb6d3e1574.js
nbdefense_jupyter/labextension/static/remoteEntry.52422cb5d5bada194ec0.js
nbdefense_jupyter/labextension/static/style.js
nbdefense_jupyter/labextension/static/third-party-licenses.json
nbdefense_jupyter-1.0.4.data/data/share/jupyter/labextensions/nbdefense-jupyter/package.json
nbdefense_jupyter-1.0.4.data/data/share/jupyter/labextensions/nbdefense-jupyter/schemas/nbdefense-jupyter/package.json.orig
nbdefense_jupyter-1.0.4.data/data/share/jupyter/labextensions/nbdefense-jupyter/schemas/nbdefense-jupyter/plugin.json
nbdefense_jupyter-1.0.4.data/data/share/jupyter/labextensions/nbdefense-jupyter/static/239.1c003b0dfd58bc7823a8.js
nbdefense_jupyter-1.0.4.data/data/share/jupyter/labextensions/nbdefense-jupyter/static/355.e71f4acc9570680d68e9.js
nbdefense_jupyter-1.0.4.data/data/share/jupyter/labextensions/nbdefense-jupyter/static/452.26450d70ddf6735bc3a7.js
nbdefense_jupyter-1.0.4.dist-info/METADATA
nbdefense_jupyter-1.0.4.dist-info/WHEEL
nbdefense_jupyter-1.0.4.dist-info/licenses/LICENSE
nbdefense_jupyter-1.0.4.dist-info/RECORD
