Metadata-Version: 2.1
Name: nbdefense_jupyter
Version: 1.0.4
Summary: NB Defense Jupyter Lab Extension
Project-URL: Homepage, https://protectai.com
Project-URL: Bug Tracker, https://protectai.com/contact-us
Project-URL: Repository, https://github.com/protectai/nbdefense-jupyter.git
Author-email: ProtectAI <support@protectai.com>
License:                                  Apache License
License-File: LICENSE
Classifier: Framework :: Jupyter
Classifier: Framework :: Jupyter :: JupyterLab
Classifier: Framework :: Jupyter :: JupyterLab :: 3
Classifier: Framework :: Jupyter :: JupyterLab :: Extensions
Classifier: Framework :: Jupyter :: JupyterLab :: Extensions :: Prebuilt
Classifier: Programming Language :: Python
Classifier: Programming Language :: Python :: 3
Classifier: Programming Language :: Python :: 3.7
Classifier: Programming Language :: Python :: 3.8
Classifier: Programming Language :: Python :: 3.9
Classifier: Programming Language :: Python :: 3.10
Requires-Python: <3.11,>=3.7.1
Requires-Dist: nbdefense==1.0.4
Provides-Extra: dev
Requires-Dist: black==22.8.0; extra == 'dev'
Requires-Dist: jupyterlab<4.0.0,>=3.1; extra == 'dev'
Requires-Dist: pre-commit==2.20.0; extra == 'dev'
Provides-Extra: test
Requires-Dist: pytest; extra == 'test'
Requires-Dist: pytest-cov; extra == 'test'
